prison/__init__.py
prison/__version__.py
prison/constants.py
prison/decoder.py
prison/encoder.py
prison/utils.py
prison-0.2.0.dist-info/LICENSE
prison-0.2.0.dist-info/METADATA
prison-0.2.0.dist-info/WHEEL
prison-0.2.0.dist-info/top_level.txt
prison-0.2.0.dist-info/RECORD
