Metadata-Version: 2.1
Name: prison
Version: 0.2.0
Summary: Rison encoder/decoder
Home-page: https://github.com/betodealmeida/python-rison
Author: Beto Dealmeida
Author-email: beto@dealmeida.net
License: MIT
Platform: UNKNOWN
Classifier: License :: OSI Approved :: MIT License
Classifier: Programming Language :: Python
Classifier: Programming Language :: Python :: 2.6
Classifier: Programming Language :: Python :: 2.7
Classifier: Programming Language :: Python :: 3
Classifier: Programming Language :: Python :: 3.3
Classifier: Programming Language :: Python :: 3.4
Classifier: Programming Language :: Python :: 3.5
Classifier: Programming Language :: Python :: 3.6
Classifier: Programming Language :: Python :: Implementation :: CPython
Classifier: Programming Language :: Python :: Implementation :: PyPy
Requires-Dist: six
Provides-Extra: dev
Requires-Dist: nose ; extra == 'dev'
Requires-Dist: pipreqs ; extra == 'dev'
Requires-Dist: twine ; extra == 'dev'
